pylsp_autoflake/__init__.py
pylsp_autoflake/plugin.py
pylsp_autoflake-0.1.1.dist-info/LICENSE
pylsp_autoflake-0.1.1.dist-info/METADATA
pylsp_autoflake-0.1.1.dist-info/WHEEL
pylsp_autoflake-0.1.1.dist-info/entry_points.txt
pylsp_autoflake-0.1.1.dist-info/top_level.txt
pylsp_autoflake-0.1.1.dist-info/RECORD
