Metadata-Version: 2.1
Name: pylsp-autoflake
Version: 0.1.1
Summary: autoflake plugin for the Python LSP Server
Author-email: bdvllrs <bdvllrs@gmail.com>
License: MIT
Project-URL: Homepage, https://github.com/bdvllrs/pylsp-autoflake
Project-URL: Bug Tracker, https://github.com/bdvllrs/pylsp-autoflake/issues
Requires-Python: >=3.7
License-File: LICENSE
Requires-Dist: python-lsp-server
Requires-Dist: autoflake >=2.2.1
Provides-Extra: dev
Requires-Dist: pytest ; extra == 'dev'
